ecobici/__init__.py
ecobici/ecobici.py
ecobici/test.py
ecobici-0.0.3.dist-info/METADATA
ecobici-0.0.3.dist-info/RECORD
ecobici-0.0.3.dist-info/WHEEL
ecobici-0.0.3.dist-info/top_level.txt
