Metadata-Version: 2.1
Name: ecobici
Version: 0.0.3
Summary: This is a python wrapper for the ecobici api
Home-page: https://github.com/sainoba/ecobici_py
Author: Marco Nila
Author-email: contact.marconila@gmail.com
License: UNKNOWN
Platform: UNKNOWN
Classifier: Programming Language :: Python :: 3
Classifier: License :: OSI Approved :: MIT License
Classifier: Operating System :: OS Independent
